hessQuik/__init__.py
hessQuik/activations/__init__.py
hessQuik/activations/antiTanh_activation.py
hessQuik/activations/hessQuik_activation_function.py
hessQuik/activations/identity_activation.py
hessQuik/activations/quadratic_activation.py
hessQuik/activations/sigmoid_activation.py
hessQuik/activations/softplus_activation.py
hessQuik/activations/tanh_activation.py
hessQuik/layers/__init__.py
hessQuik/layers/hessQuik_layer.py
hessQuik/layers/icnn_layer.py
hessQuik/layers/quadratic_icnn_layer.py
hessQuik/layers/quadratic_layer.py
hessQuik/layers/resnet_layer.py
hessQuik/layers/single_layer.py
hessQuik/networks/__init__.py
hessQuik/networks/fully_connected_network.py
hessQuik/networks/hessQuik_network.py
hessQuik/networks/icnn_network.py
hessQuik/networks/resnet_network.py
hessQuik/utils/__init__.py
hessQuik/utils/data.py
hessQuik/utils/directional_derivative_check.py
hessQuik/utils/input_derivative_check.py
hessQuik/utils/input_derivative_check_laplacian.py
hessQuik/utils/laplacian_check.py
hessQuik/utils/network_derivative_check.py
hessQuik/utils/timing.py
hessQuik/utils/training.py
hessQuik/utils/utils.py
hessQuik-0.0.6.dist-info/LICENSE
hessQuik-0.0.6.dist-info/METADATA
hessQuik-0.0.6.dist-info/WHEEL
hessQuik-0.0.6.dist-info/top_level.txt
hessQuik-0.0.6.dist-info/RECORD
