Metadata-Version: 2.1
Name: hessQuik
Version: 0.0.6
Summary: AD-free gradient and Hessian computations
Home-page: https://github.com/elizabethnewman/hessQuik
Author: Elizabeth Newman
Author-email: elizabeth.newman@emory.edu
License: MIT
License-File: LICENSE
Requires-Dist: torch
Provides-Extra: docs
Requires-Dist: Sphinx (>=3.0.0) ; extra == 'docs'
Requires-Dist: docutils ; extra == 'docs'
Requires-Dist: pylons-sphinx-themes (>=1.0.8) ; extra == 'docs'
Requires-Dist: pylons-sphinx-latesturl ; extra == 'docs'
Requires-Dist: repoze.sphinx.autointerface ; extra == 'docs'
Requires-Dist: sphinxcontrib-autoprogram ; extra == 'docs'
Provides-Extra: interactive
Requires-Dist: numpy ; extra == 'interactive'
Requires-Dist: matplotlib ; extra == 'interactive'
